shardate/__init__.py
shardate/dates.py
shardate/shardate.py
shardate/utils.py
shardate-2025.9.20.dist-info/METADATA
shardate-2025.9.20.dist-info/WHEEL
shardate-2025.9.20.dist-info/licenses/LICENSE
shardate-2025.9.20.dist-info/RECORD
