Metadata-Version: 2.4
Name: shardate
Version: 2025.9.20
Summary: A lightweight Python library for efficiently reading year-month-day partitioned Parquet datasets.
Project-URL: Homepage, https://github.com/yoichiojima-2/shardate
Project-URL: Repository, https://github.com/yoichiojima-2/shardate
Project-URL: Issues, https://github.com/yoichiojima-2/shardate/issues
Author-email: Yoichi Ojima <yoichiojima@gmail.com>
License: MIT
License-File: LICENSE
Keywords: data,parquet,partitioning,pyspark
Classifier: Development Status :: 3 - Alpha
Classifier: License :: OSI Approved :: MIT License
Classifier: Programming Language :: Python :: 3
Classifier: Programming Language :: Python :: 3.12
Requires-Python: >=3.12
Requires-Dist: pyspark>=4.0.0
Requires-Dist: python-dateutil>=2.9.0.post0
